cnd_cr_object/__init__.py
cnd_cr_object/__version__.py
cnd_cr_object/cr_object.py
cnd_cr_object-1.0.1.dist-info/METADATA
cnd_cr_object-1.0.1.dist-info/WHEEL
cnd_cr_object-1.0.1.dist-info/RECORD
